{
  "users" :[
  {
    "id" :1,
    "name" : "nguyen van an",
    "email" : "nguyenvnaan@gmail.com",
    "phone" : "0912345678",
    "Avatar": "Http://example.com/avatar/an.jpg",
    "dateOfBirth" : "1990-05-15",
  },
  {
    "id" :2,
    "name" : "nguyen van kan",
    "email" : "nguyenvnakan@gmail.com",
    "phone" : "0912345678",
    "Avatar": "Http://example.com/avatar/an.jpg",
    "dateOfBirth" : "1990-05-15",
  },
  {
    "id" :3,
    "name" : "nguyen van han",
    "email" : "nguyenvnahan@gmail.com",
    "phone" : "0912345678",
    "Avatar": "Http://example.com/avatar/an.jpg",
    "dateOfBirth" : "1990-05-15",
  },
  {
    "id" :4,
    "name" : "nguyen van ban",
    "email" : "nguyenvnaban@gmail.com",
    "phone" : "0912345678",
    "Avatar": "Http://example.com/avatar/an.jpg",
    "dateOfBirth" : "1990-05-15",
  },
  {
    "id" :5,
    "name" : "nguyen van ean",
    "email" : "nguyenvnaean@gmail.com",
    "phone" : "0912345678",
    "Avatar": "Http://example.com/avatar/an.jpg",
    "dateOfBirth" : "1990-05-15",
  },
  {
    "id" :6,
    "name" : "nguyen van tan",
    "email" : "nguyenvnatan@gmail.com",
    "phone" : "0912345678",
    "Avatar": "Http://example.com/avatar/an.jpg",
    "dateOfBirth" : "1990-05-15",
  },
  {
    "id" :7,
    "name" : "nguyen van van",
    "email" : "nguyenvnavan@gmail.com",
    "phone" : "0912345678",
    "Avatar": "Http://example.com/avatar/an.jpg",
    "dateOfBirth" : "1990-05-15",
  },{
    "id" :8,
    "name" : "nguyen van in",
    "email" : "nguyenvnain@gmail.com",
    "phone" : "0912345678",
    "Avatar": "Http://example.com/avatar/an.jpg",
    "dateOfBirth" : "1990-05-15",
  },
  {
    "id" :9,
    "name" : "nguyen van ang",
    "email" : "nguyenvnaang@gmail.com",
    "phone" : "0912345678",
    "Avatar": "Http://example.com/avatar/an.jpg",
    "dateOfBirth" : "1990-05-15",
  },
  {
    "id" :10,
    "name" : "nguyen van anh",
    "email" : "nguyenvnaanh@gmail.com",
    "phone" : "0912345678",
    "Avatar": "Http://example.com/avatar/an.jpg",
    "dateOfBirth" : "1990-05-15",
  },
]
}
  
  
  
